{
  "8": {
    "slug": "zhovti-poperedzhennia-pivden-30-gradusiv-grozy-9-kvitnia-2026",
    "msg_id": 19,
    "type": "weather",
    "title": "Жовті попередження на Півдні, до 30°C у Центрі — і грози після обіду"
  },
  "9": {
    "slug": "34-tysiachi-zayavok-vidnovlennia-zhytla-buri-seguro-kviten-2026",
    "msg_id": 20,
    "type": "news",
    "title": "34 тисячі заявок на відновлення житла після бурь — президент Сеґуру підштовхує уряд до прискорення виплат"
  },
  "10": {
    "slug": "via-verde-immihraciya-1-rik-rezultaty-3328-viz-kviten-2026",
    "msg_id": 21,
    "type": "news",
    "title": "Програма «Via Verde» для імміграції: за рік — 3 328 віз, сільське господарство лідирує"
  },
  "11": {
    "slug": "parlament-isp-palyne-znyzhka-stavky-30-chervnia-2026",
    "msg_id": 22,
    "type": "news",
    "title": "Парламент одноголосно знизив ISP на пальне — що це означає для вас"
  },
  "12": {
    "slug": "pidhotovka-do-lita-2026-ochystka-dilanok-shtrafy-pozhezhi-instrukcia",
    "msg_id": 23,
    "type": "material",
    "title": "Як підготуватися до пожежонебезпечного літа 2026: дедлайни, штрафи до €25 000 і що робити вже зараз"
  },
  "13": {
    "slug": "portugalia-fregat-f16-baltyka-nato-brilliant-shield-kviten-2026",
    "msg_id": 24,
    "type": "news",
    "title": "Португалія відправила фрегат і винищувачі F-16 до Балтики для моніторингу Росії"
  }
}